sphinxcontrib/exceltable/__init__.py
sphinxcontrib_exceltable-0.3.0.dist-info/LICENSE
sphinxcontrib_exceltable-0.3.0.dist-info/METADATA
sphinxcontrib_exceltable-0.3.0.dist-info/WHEEL
sphinxcontrib_exceltable-0.3.0.dist-info/top_level.txt
sphinxcontrib_exceltable-0.3.0.dist-info/RECORD
