Metadata-Version: 2.1
Name: sphinxcontrib-exceltable
Version: 0.3.0
Summary: Support for including Excel spreadsheets into Sphinx documents
Home-page: https://packages.python.org/sphinxcontrib-exceltable
Download-URL: http://pypi.python.org/pypi/sphinxcontrib-exceltable
Author: Juha Mustonen
Author-email: juha.p.mustonen@gmail.com
Project-URL: GitHub: repo, https://github.com/sphinx-contrib/exceltable
Project-URL: GitHub: issues, https://github.com/sphinx-contrib/exceltable/issues
Classifier: Development Status :: 4 - Beta
Classifier: Environment :: Console
Classifier: Environment :: Web Environment
Classifier: Intended Audience :: Developers
Classifier: License :: OSI Approved :: MIT License
Classifier: Operating System :: OS Independent
Classifier: Programming Language :: Python
Classifier: Programming Language :: Python :: 2
Classifier: Programming Language :: Python :: 3
Classifier: Topic :: Documentation
Classifier: Topic :: Utilities
Requires-Python: <4,>=3.8
License-File: LICENSE
Requires-Dist: Sphinx (>=5)
Requires-Dist: xlrd
Requires-Dist: docutils
Provides-Extra: test
Requires-Dist: pytest ; extra == 'test'
